{
    "scenes": [
        {
            "title": "Picasso, jeune peintre",
            "unlocked": "true",
            "number": "0",
            "date": "1890 - 1910",
            "description": "Au commencement, Sangoku est un jeune garcon tres naif et innocent. Il vit isole dans la foret et a ete eleve par son grand pere adoptif Sangohan. Bien que tres petit, il a une force phenomenale et chasse des monstres ou peche d'enormes poissons pour son petit dejeuner.\n\rUn jour, il rencontre Bulma. Elle le persuade de l'accompagner pour rechercher les sept boules de cristal legendaires. Une fois reunies, elles permettent l'apparition d'un immense dragon, Shenron qui peut exaucer un souhait quelconque. Bulma a construit un radar qui detecte les boules. Le periple de Sangoku et Bulma commence.\n\rIls font la connaissance d'un maitre des arts martiaux, Tortue Geniale, qui offre un nuage magique a Sangoku. En chemin, ils doivent combattre Oolong un cochon capable de se transformer puis Yamcha, un farouche bandit qui est accompagne de Plume. Ils deviennent tous de bons amis par la suite.\n\rLeurs premiers grands ennemis sont Pilaf et ses deux acolytes, tous des etres teigneux et miserables partis eux aussi a la quete des boules de cristal. Pilaf veut devenir le maitre du monde mais ses reves de conquetes et son chateau sont aneantis par Sangoku, metamorphose en singe geant devastateur pendant une nuit de pleine Lune.\n\rApres ses aventures. Sangoku part s'entrainer chez Tortue Geniale. Un autre garcon, Krilin vient s'entrainer avec lui. Apres 8 mois d'entrainement, les deux eleves participent a leur premier tournoi des arts martiaux, mais sont battus par leur maitre, inscrit aux epreuves sous une fausse identite.\n\rSangoku decide alors de partir rechercher la boule de son grand pere et se retrouve face a l'armee de ruban rouge. Son commandant en chef, un terrible dictateur, veut s'emparer de toutes les boules de cristal. Sangoku recupere plusieurs boules et defait les meilleurs generaux de l'armee mais il doit s'avouer vaincu devant Tao Pai Pai, un redoutable tueur a gages.\n\rAfin d'acquerir plus de forces, Sangoku grimpe au sommet de la tour Karine afin de boire l'eau sacree gardee par maitre Karine. Il parvient a boire l'eau en seulement trois jours durant lesquels sa force a grandement augmente et il redescend pour terrasser Tao Pai Pai et le QG du ruban rouge.",
            "videoType": "mov",
            "trackerStarts": [19, 40, 78],
            "trackers": [
                {
                    "workId": "0",
                    "positions": [
                        [0, 430, 142],
                        [1, 429, 142],
                        [2, 428, 142],
                        [3, 427, 142],
                        [4, 426, 142],
                        [5, 425, 142],
                        [6, 424, 142],
                        [7, 423, 142],
                        [8, 422, 142],
                        [9, 421, 142],
                        [10, 420, 142],
                        [11, 419, 142],
                        [12, 418, 142],
                        [13, 417, 142],
                        [14, 416, 142],
                        [15, 415, 142],
                        [16, 414, 142],
                        [17, 413, 142],
                        [18, 412, 142],
                        [19, 411, 142],
                        [20, 410, 142],
                        [21, 409, 142],
                        [22, 408, 142],
                        [23, 407, 142],
                        [24, 406, 142],
                        [25, 405, 142],
                        [26, 404, 142],
                        [27, 403, 142],
                        [28, 402, 142],
                        [29, 401, 142],
                        [30, 400, 142],
                        [31, 399, 142],
                        [32, 398, 142],
                        [33, 397, 142],
                        [34, 396, 142],
                        [35, 395, 142],
                        [36, 394, 142],
                        [37, 393, 142],
                        [38, 392, 142],
                        [39, 391, 142],
                        [40, 390, 142],
                        [41, 389, 142],
                        [42, 388, 142],
                        [43, 387, 142],
                        [44, 386, 142],
                        [45, 385, 142],
                        [46, 384, 142],
                        [47, 383, 142],
                        [48, 382, 142],
                        [49, 381, 142],
                        [50, 380, 142],
                        [51, 379, 142],
                        [52, 378, 142],
                        [53, 377, 142],
                        [54, 376, 142],
                        [55, 375, 142],
                        [56, 374, 142],
                        [57, 373, 142],
                        [58, 372, 142],
                        [59, 371, 142],
                        [60, 370, 142],
                        [61, 369, 142],
                        [62, 368, 142],
                        [63, 367, 142],
                        [64, 366, 142],
                        [65, 365, 142],
                        [66, 364, 142],
                        [67, 363, 142],
                        [68, 362, 142],
                        [69, 361, 142],
                        [70, 360, 142],
                        [71, 359, 142],
                        [72, 358, 142],
                        [73, 357, 142],
                        [74, 356, 142],
                        [75, 355, 142],
                        [76, 354, 142],
                        [77, 353, 142],
                        [78, 352, 142],
                        [79, 351, 142],
                        [80, 350, 142],
                        [81, 349, 142],
                        [82, 348, 142],
                        [83, 347, 142],
                        [84, 346, 142],
                        [85, 345, 142],
                        [86, 344, 142],
                        [87, 343, 142],
                        [88, 342, 142],
                        [89, 341, 142],
                        [90, 340, 142],
                        [91, 339, 142],
                        [92, 338, 142],
                        [93, 337, 142],
                        [94, 336, 142],
                        [95, 335, 142],
                        [96, 334, 142],
                        [97, 333, 142],
                        [98, 332, 142],
                        [99, 331, 142],
                        [100, 330, 142],
                        [101, 329, 142],
                        [102, 328, 142],
                        [103, 327, 142],
                        [104, 326, 142],
                        [105, 325, 142],
                        [106, 324, 142],
                        [107, 323, 142],
                        [108, 322, 142],
                        [109, 321, 142],
                        [110, 320, 142],
                        [111, 319, 142],
                        [112, 318, 142],
                        [113, 317, 142],
                        [114, 316, 142],
                        [115, 315, 142],
                        [116, 314, 142],
                        [117, 313, 142],
                        [118, 312, 142],
                        [119, 311, 142],
                        [120, 310, 142],
                        [121, 309, 142],
                        [122, 308, 142],
                        [123, 307, 142],
                        [124, 306, 142],
                        [125, 305, 142],
                        [126, 304, 142],
                        [127, 303, 142],
                        [128, 302, 142],
                        [129, 301, 142],
                        [130, 300, 142],
                        [131, 299, 142],
                        [132, 298, 142],
                        [133, 297, 142],
                        [134, 296, 142],
                        [135, 295, 142],
                        [136, 294, 142],
                        [137, 293, 142],
                        [138, 292, 142],
                        [139, 291, 142],
                        [140, 290, 142],
                        [141, 289, 142],
                        [142, 288, 142],
                        [143, 287, 142],
                        [144, 286, 142],
                        [145, 285, 142],
                        [146, 284, 142],
                        [147, 283, 142],
                        [148, 282, 142],
                        [149, 281, 142],
                        [150, 280, 142],
                        [151, 279, 142],
                        [152, 278, 142],
                        [153, 277, 142],
                        [154, 276, 142],
                        [155, 275, 142],
                        [156, 274, 142],
                        [157, 273, 142],
                        [158, 272, 142],
                        [159, 271, 142],
                        [160, 270, 142],
                        [161, 269, 142],
                        [162, 268, 142],
                        [163, 267, 142],
                        [164, 266, 142],
                        [165, 265, 142],
                        [166, 264, 142],
                        [167, 263, 142],
                        [168, 262, 142],
                        [169, 261, 142],
                        [170, 260, 142],
                        [171, 259, 142],
                        [172, 258, 142],
                        [173, 257, 142],
                        [174, 256, 142],
                        [175, 255, 142],
                        [176, 254, 142],
                        [177, 253, 142],
                        [178, 252, 142],
                        [179, 251, 142],
                        [180, 250, 142],
                        [181, 249, 142],
                        [182, 248, 142],
                        [183, 247, 142],
                        [184, 246, 142],
                        [185, 245, 142],
                        [186, 244, 142],
                        [187, 243, 142],
                        [188, 242, 142],
                        [189, 241, 142],
                        [190, 240, 142],
                        [191, 239, 142],
                        [192, 238, 142],
                        [193, 237, 142],
                        [194, 236, 142],
                        [195, 235, 142],
                        [196, 234, 142],
                        [197, 233, 142],
                        [198, 232, 142],
                        [199, 231, 142],
                        [200, 230, 142],
                        [201, 229, 142],
                        [202, 228, 142],
                        [203, 227, 142],
                        [204, 226, 142],
                        [205, 225, 142],
                        [206, 224, 142],
                        [207, 223, 142],
                        [208, 222, 142],
                        [209, 221, 142],
                        [210, 220, 142],
                        [211, 219, 142],
                        [212, 218, 142],
                        [213, 217, 142],
                        [214, 216, 142],
                        [215, 215, 142],
                        [216, 214, 142],
                        [217, 213, 142],
                        [218, 212, 142],
                        [219, 211, 142],
                        [220, 210, 142],
                        [221, 209, 142],
                        [222, 208, 142],
                        [223, 207, 142],
                        [224, 206, 142],
                        [225, 205, 142],
                        [226, 204, 142],
                        [227, 203, 142],
                        [228, 202, 142],
                        [229, 201, 142],
                        [230, 200, 142],
                        [231, 199, 142],
                        [232, 198, 142],
                        [233, 197, 142],
                        [234, 196, 142],
                        [235, 195, 142],
                        [236, 194, 142],
                        [237, 193, 142],
                        [238, 192, 142],
                        [239, 191, 142],
                        [240, 190, 142],
                        [241, 189, 142],
                        [242, 188, 142],
                        [243, 187, 142],
                        [244, 186, 142],
                        [245, 185, 142],
                        [246, 184, 142],
                        [247, 183, 142],
                        [248, 182, 142],
                        [249, 181, 142],
                        [250, 180, 142],
                        [251, 179, 142],
                        [252, 178, 142],
                        [253, 177, 142],
                        [254, 176, 142],
                        [255, 175, 142],
                        [256, 174, 142],
                        [257, 173, 142],
                        [258, 172, 142],
                        [259, 171, 142],
                        [260, 170, 142],
                        [261, 169, 142],
                        [262, 168, 142],
                        [263, 167, 142],
                        [264, 166, 142],
                        [265, 165, 142],
                        [266, 164, 142],
                        [267, 163, 142],
                        [268, 162, 142],
                        [269, 161, 142],
                        [270, 160, 142],
                        [271, 159, 142],
                        [272, 158, 142],
                        [273, 157, 142],
                        [274, 156, 142],
                        [275, 155, 142],
                        [276, 154, 142],
                        [277, 153, 142],
                        [278, 152, 142],
                        [279, 151, 142],
                        [280, 150, 142],
                        [281, 149, 142],
                        [282, 148, 142],
                        [283, 147, 142],
                        [284, 146, 142],
                        [285, 145, 142],
                        [286, 144, 142],
                        [287, 143, 142],
                        [288, 142, 142],
                        [289, 141, 142],
                        [290, 140, 142],
                        [291, 139, 142],
                        [292, 138, 142],
                        [293, 137, 142],
                        [294, 136, 142],
                        [295, 135, 142],
                        [296, 134, 142],
                        [297, 133, 142],
                        [298, 132, 142],
                        [299, 131, 142]
                    ]
                }
            ]
        },
        {
            "title": "La période bleue",
            "unlocked": "false",
            "number": "1",
            "date": "1890 - 1910",
            "description": "Apres le tournoi, une petite fete est organisee mais tout est gache par un drame : Krilin est assassine par un inconnu. Sangoku, part a la poursuite du tueur qui elimine un par un les autres participants. Il a ete envoye par Piccolo, le diable en personne. En chemin, Sangoku se lie d'amitie avec Yajirobe, qui permet a Sangoku de s'enfuir apres sa defaite face a Piccolo.\n\rPiccolo est parti a la recherche des sept boules de cristal afin de gagner la vie eternelle. Tortue geniale, Tenshinhan et Chaozu font cause commune et s'empare d'un maximum de boules avant lui. Tortue geniale connait une technique de combat afin d'emprisonner le diable dans un autocuiseur:le mafuba mais la technique echoue et Tortue geniale est tue ainsi que Chaozu. Les boules etant reunies devant Piccolo, le dragon Shenron realise son souhait de jeunesse eternelle.\n\rPour eviter que quelqu'un d'autre puisse reunir les boules, Piccolo detruit le dragon. Entre temps, Sangoku est alle revoir Karine qui lui propose de boire un elixir qui reveille les forces cachees mais qui est egalement un poison si on est pas pret a le boire. Sangoku boit et arrive a temps pour sauver Tenshinhan et battre Piccolo. Avant de trepasser, le monstre a helas le temps de creer un oeuf qui donnera naissance a son successeur (ou plutot sa reincarnation).",
            "videoType": "mp4",
            "trackerStarts": [19, 40, 78],
            "trackers": [
                {
                    "workId": "1",
                    "positions": [
                        [0, 276, 207],
                        [1, 276, 207],
                        [2, 276, 207],
                        [3, 276, 207],
                        [4, 276, 207],
                        [5, 276, 207],
                        [6, 276, 207],
                        [7, 276, 207],
                        [8, 276, 207],
                        [9, 276, 207],
                        [10, 276, 207],
                        [11, 276, 207],
                        [12, 276, 207],
                        [13, 276, 207],
                        [14, 276, 207],
                        [15, 276, 207],
                        [16, 276, 207],
                        [17, 276, 207],
                        [18, 276, 207],
                        [19, 276, 207],
                        [20, 276, 207],
                        [21, 276, 207],
                        [22, 276, 207],
                        [23, 276, 207],
                        [24, 276, 207],
                        [25, 276, 207],
                        [26, 276, 207],
                        [27, 276, 207],
                        [28, 276, 207],
                        [29, 276, 207],
                        [30, 276, 207],
                        [31, 276, 207],
                        [32, 276, 207],
                        [33, 276, 207],
                        [34, 276, 207],
                        [35, 276, 207],
                        [36, 276, 207],
                        [37, 276, 207],
                        [38, 276, 207],
                        [39, 276, 207],
                        [40, 276, 207],
                        [41, 276, 207],
                        [42, 276, 207],
                        [43, 276, 207],
                        [44, 276, 207],
                        [45, 276, 207],
                        [46, 276, 207],
                        [47, 276, 207],
                        [48, 276, 207],
                        [49, 276, 207],
                        [50, 276, 207],
                        [51, 276, 207],
                        [52, 276, 207],
                        [53, 276, 207],
                        [54, 276, 207],
                        [55, 276, 207],
                        [56, 276, 207],
                        [57, 276, 207],
                        [58, 276, 207],
                        [59, 276, 207],
                        [60, 276, 207],
                        [61, 276, 207],
                        [62, 276, 207],
                        [63, 276, 207],
                        [64, 276, 207],
                        [65, 276, 207],
                        [66, 276, 207],
                        [67, 276, 207],
                        [68, 276, 207],
                        [69, 276, 207],
                        [70, 276, 207],
                        [71, 276, 207],
                        [72, 276, 207],
                        [73, 276, 207],
                        [74, 276, 207],
                        [75, 276, 207],
                        [76, 276, 207],
                        [77, 276, 207],
                        [78, 276, 207],
                        [79, 276, 207],
                        [80, 276, 207],
                        [81, 276, 207],
                        [82, 276, 207],
                        [83, 276, 207],
                        [84, 276, 207],
                        [85, 276, 207],
                        [86, 276, 207],
                        [87, 276, 207],
                        [88, 276, 207],
                        [89, 276, 207],
                        [90, 276, 207],
                        [91, 276, 207],
                        [92, 276, 207],
                        [93, 276, 207],
                        [94, 276, 207],
                        [95, 276, 207],
                        [96, 276, 207],
                        [97, 276, 207],
                        [98, 276, 207],
                        [99, 276, 207]
                    ]
                }
            ]
        },
        {
            "title": "Scene 3",
            "unlocked": "false",
            "number": "2",
            "date": "1890 - 1910",
            "description": "",
            "videoType": "mov",
            "trackers": []
        },
        {
            "title": "Scene 4",
            "unlocked": "false",
            "number": "3",
            "date": "1890 - 1910",
            "description": "",
            "videoType": "mov",
            "trackers": []
        },
        {
            "title": "Scene 5",
            "unlocked": "false",
            "number": "4",
            "date": "1890 - 1910",
            "description": "",
            "videoType": "mov",
            "trackers": []
        },
        {
            "title": "Scene 6",
            "unlocked": "false",
            "number": "5",
            "date": "1890 - 1910",
            "description": "",
            "videoType": "mov",
            "trackers": []
        },
        {
            "title": "Scene 7",
            "unlocked": "false",
            "number": "6",
            "date": "1890 - 1910",
            "description": "",
            "videoType": "mov",
            "trackers": []
        }
    ],

    "works": [
              {
              "id": "0",
              "title": "La fillette aux pieds nus",
              "sceneNumber": "0",
              "year": "1900",
              "h": "20 m",
              "l": "30 m",
              "technical": "Huiles sur toile",
              "description": "Cette œuvre est un témoignage de sa précocité, comme le souligne Pierre Daix : « témoignage de sa précocité, et peut être aussi souvenir d’une émotion d’adolescent puisqu’il n’avait pas quatorze ans lorsqu’il la peignit « La fillette aux pieds nus atteste un métier affirmé jusqu’aux roueries pour camper cette figure assise de face en dissimulant les repères spatiaux de la chaise sur le sol. Ce qui a intéressé Pablo, ce n’est pas pourtant la seule technique, c’est d’interroger al vie de ce modèle de son âge, de vouloir à tout prix capter son avenir de femme et de la capter d’avance par ses pinceaux. Précocité déjà effrayante… » (Daix, 1987,19). Ajoutons que la Fillette anticipe sur ces centaines de « femmes assises » qu’on retrouvera tout au long de l’œuvre comme une obsession de la peinture ». (Pierre Daix, Le nouveau dictionnaire Picasso, p. 369). Joseph Palau i Fabre souligne que dans ce tableau de jeunesse « se révèlent à la fois la sympathie pour ses modèles et l’attrait de la femme, même si la féminité de cette petite mendiante est encore embryonnaire et triste. Picasso réalisa ce tableau d’après un modèle vivant dont les parents louèrent les services, montrant là l’intérêt qu’ils attachaient à la vocation de leur fils dont ils souhaitaient l’aider à prendre lui-même pleine conscience. A propos de ce tableau, le peintre déclara à Antonina Vallentin « Les pauvresses de notre pays vont toujours pieds nus, et cette fillette avait les siens couverts de cals ». (Val, P, p.20).  Cette fillette aux pieds nus, en pied au regard asymétrique bien observé, à la bouche légèrement désabusée, semble comme le nostalgique adieu de Picasso à une période de sa vie. Son premier face-à-face avec la femme est traduit avec une intense expressivité : la fillette regarde et voit autant qu’elle est regardée et vue. Ici s’ébauche déjà le problème du peintre et son modèle, que bien plus tard Picasso devait affronter à plusieurs reprises. Il ya  là deux adolescents à peu près du même âge, l’un devant l’autre, qui ne purent se dire par leur regard ce qu’ils auraient pu se dire de vive voix. Mais ces yeux ont gardé, malgré le passage du temps, toute la force d’attraction qu’ils possédaient ou que Picasso sut mettre en eux ». (Joseph Palau i Fabre, Picasso vivant. Enfance et première jeunesse d’un démiurge. 1881-1907, p.63)."
              },
              {
              "id": "1",
              "title": "La mort de Casagemas",
              "sceneNumber": "0",
              "year": "1900",
              "h": "20 m",
              "l": "30 m",
              "technical": "Huiles sur toile",
              "description": "« Le suicide de son ami Casagemas le 17 février 1901, poussa Picasso à créer tout un ensemble de tableaux dont il conserva secrètement les trois premiers jusqu’en 1965 quand il le fit reproduire dans D-B. Le premier est La mort de Casagemas, dans la palette haute en couleurs de l’exposition chez Vollard, qui doit dater de l’été 1901. Casagemas dans son cercueil et Portrait de Casagemas mort marquent l’emprise progressive du bleu (…). Ce cycle illustre la précision de la remarque de Picasso : « C’est en pensant que Casagemas était mort que je me suis mis à peindre en bleu ». (Daix, 1975, 47à) ». (Pierre Daix, Le nouveau dictionnaire Picasso, p. 228). Marie-Laure Bernadac a qualifié la mort de cet ami de sujet obsessionnel : « Cette mort va obséder progressivement Picasso. Pour l’exorciser, il réalise une série de portraits posthumes, sept toiles et de multiples dessins. (…). Le suicidé (le thème de la mort violente est fréquent dans l’art espagnol) est enveloppé dans un linceul, seul le visage vu de profil sort de l’écume. Casagemas est peint en grand plan, sur sa tempe une tache sombre, l’impact de la balle. Cassant le mouvement oblique une énorme chandelle verticale illumine tout le tableau. Symbole de l’écoulement de la vie, la bougie reviendra dans les nature-mortes de la seconde guerre mondiale. La lumière se répand sur le linceul par taches jaunes et dessine le profil ; mouvante, elle s’oppose au statisme et à la pérennité du visage. L’influence de Van Gogh est nette : la touche, les empâtements de rouge, jaune, vert et bleu. » (Marie-Laure Bernadac, Musée Picasso Paris, Les chefs d’œuvre, p. 18)."
              },
              {
              "id": "2",
              "title": "Autoportrait",
              "sceneNumber": "0",
              "year": "1900",
              "h": "20 m",
              "l": "30 m",
              "technical": "Huiles sur toile",
              "description": "Cet autoportrait est la poursuite du cycle sur Casagemas comme le souligne Pierre Daix : « Cet autoportrait, toujours conservé par Picasso le montre tel qu’il s’est vu après le retour sur soi du Cycle de la mort de Casagemas en apprenant que Manyac, qui l’avait jusque-là soutenu financièrement lui coupait les vivres. Celui-ci désapprouvait le tournant que prenait la peinture de Picasso vers ce que l’on appelle à présent la « période bleue » et dont les thèmes, le malheur et la détresse, éloignaient les acheteurs. C’est en quelque sorte un autoportrait au futur dans la misère qui ne manquerait pas de le guetter, au milieu de l’hiver si inclément de Paris. Mais s’il n’a évidemment jamais porté cette moustache et cette barbe blonde qu’il peint avec des finesses de miniaturiste pour aggraver l’aspect hâve, creusé par la faim, de son visage, nous savons aujourd’hui à quel point il s’est alors « donné » cette tête-là. »  (Pierre Daix, Le nouveau dictionnaire Picasso, p. 68). Marie-Laure Bernadac revient sur l’importance de l’autoportrait dans l’œuvre picassien : « S’inscrivant dans la lignée de l’œuvre de ses illustres prédécesseurs (Rembrandt, Van Gogh) Picasso marque pour ce thème une prédilection, puisque l’on retrouvera tout au long de sa longue existence, des images distinctes de lui-même, révélatrices de chaque étape de sa vie et de son œuvre. Peint lors du second séjour à Paris, en hiver 1901, cet autoportrait qui marque le début de la période bleue est le dernier d’une série, avant le départ pour Barcelone en janvier 1902. » (Marie-Laure Bernadac, Musée Picasso Paris, Les chefs d’œuvre, p. 20)."
              },
              {
              "id": "3",
              "title": "Autoportrait, automne 1906",
              "sceneNumber": "1",
              "year": "1900",
              "h": "20 m",
              "l": "30 m",
              "technical": "Huiles sur toile",
              "description": "Pour Pierre Daix, Picasso a toujours pris « son visage comme banc d’essai de ses percées figuratives. L’entreprise de réduction du visage à son masque a commencé au début de l’été 1906 à Gosol sur le visage de (…) Fernande, à partir d’une réflexion sur les sculptures ibériques révélées au Louvre fin 1905. Elle aboutit à Paros à toute une série d’autoportraits où Picasso réduit son propre visage à son masque, c’est-à-dire à des volumes neutralisés. (…) En dépit de cette première référence à l’art nègre – mais à l’époque pour Picasso, le primitivisme est une recherche générale où se confondent des éléments venus de sources pour nous géographiquement et historiquement différentes –, les autoportraits de cette séquence sont essentiellement ibériques. La chevelure est toujours réduite au minimum, à son insertion sur la tête. Le cou est massif et le buste statique. » (Pierre Daix, Le nouveau dictionnaire Picasso, p. 72). Marie-Laure Bernadac précise que ce corps est « comme une architecture : c’est un carré délimité par trois traits sombres formés par les arêtes des bras et les clavicules ; dont le centre coïncide avec le croisement des muscles pectoraux et de la ligne médiane du buste. Le cou est traité comme un cylindre (…). » (Marie-Laure Bernadac, Musée Picasso Paris, Les chefs d’œuvre, p. 28). "
              },
              {
              "id": "4",
              "title": "La fillette aux pieds nus",
              "sceneNumber": "1",
              "year": "1900",
              "h": "20 m",
              "l": "30 m",
              "technical": "Huiles sur toile",
              "description": "Cette œuvre est un témoignage de sa précocité, comme le souligne Pierre Daix : « témoignage de sa précocité, et peut être aussi souvenir d’une émotion d’adolescent puisqu’il n’avait pas quatorze ans lorsqu’il la peignit « La fillette aux pieds nus atteste un métier affirmé jusqu’aux roueries pour camper cette figure assise de face en dissimulant les repères spatiaux de la chaise sur le sol. Ce qui a intéressé Pablo, ce n’est pas pourtant la seule technique, c’est d’interroger al vie de ce modèle de son âge, de vouloir à tout prix capter son avenir de femme et de la capter d’avance par ses pinceaux. Précocité déjà effrayante… » (Daix, 1987,19). Ajoutons que la Fillette anticipe sur ces centaines de « femmes assises » qu’on retrouvera tout au long de l’œuvre comme une obsession de la peinture ». (Pierre Daix, Le nouveau dictionnaire Picasso, p. 369). Joseph Palau i Fabre souligne que dans ce tableau de jeunesse « se révèlent à la fois la sympathie pour ses modèles et l’attrait de la femme, même si la féminité de cette petite mendiante est encore embryonnaire et triste. Picasso réalisa ce tableau d’après un modèle vivant dont les parents louèrent les services, montrant là l’intérêt qu’ils attachaient à la vocation de leur fils dont ils souhaitaient l’aider à prendre lui-même pleine conscience. A propos de ce tableau, le peintre déclara à Antonina Vallentin « Les pauvresses de notre pays vont toujours pieds nus, et cette fillette avait les siens couverts de cals ». (Val, P, p.20).  Cette fillette aux pieds nus, en pied au regard asymétrique bien observé, à la bouche légèrement désabusée, semble comme le nostalgique adieu de Picasso à une période de sa vie. Son premier face-à-face avec la femme est traduit avec une intense expressivité : la fillette regarde et voit autant qu’elle est regardée et vue. Ici s’ébauche déjà le problème du peintre et son modèle, que bien plus tard Picasso devait affronter à plusieurs reprises. Il ya  là deux adolescents à peu près du même âge, l’un devant l’autre, qui ne purent se dire par leur regard ce qu’ils auraient pu se dire de vive voix. Mais ces yeux ont gardé, malgré le passage du temps, toute la force d’attraction qu’ils possédaient ou que Picasso sut mettre en eux ». (Joseph Palau i Fabre, Picasso vivant. Enfance et première jeunesse d’un démiurge. 1881-1907, p.63)."
              },
              {
              "id": "5",
              "title": "La mort de Casagemas",
              "sceneNumber": "1",
              "year": "1900",
              "h": "20 m",
              "l": "30 m",
              "technical": "Huiles sur toile",
              "description": "« Le suicide de son ami Casagemas le 17 février 1901, poussa Picasso à créer tout un ensemble de tableaux dont il conserva secrètement les trois premiers jusqu’en 1965 quand il le fit reproduire dans D-B. Le premier est La mort de Casagemas, dans la palette haute en couleurs de l’exposition chez Vollard, qui doit dater de l’été 1901. Casagemas dans son cercueil et Portrait de Casagemas mort marquent l’emprise progressive du bleu (…). Ce cycle illustre la précision de la remarque de Picasso : « C’est en pensant que Casagemas était mort que je me suis mis à peindre en bleu ». (Daix, 1975, 47à) ». (Pierre Daix, Le nouveau dictionnaire Picasso, p. 228). Marie-Laure Bernadac a qualifié la mort de cet ami de sujet obsessionnel : « Cette mort va obséder progressivement Picasso. Pour l’exorciser, il réalise une série de portraits posthumes, sept toiles et de multiples dessins. (…). Le suicidé (le thème de la mort violente est fréquent dans l’art espagnol) est enveloppé dans un linceul, seul le visage vu de profil sort de l’écume. Casagemas est peint en grand plan, sur sa tempe une tache sombre, l’impact de la balle. Cassant le mouvement oblique une énorme chandelle verticale illumine tout le tableau. Symbole de l’écoulement de la vie, la bougie reviendra dans les nature-mortes de la seconde guerre mondiale. La lumière se répand sur le linceul par taches jaunes et dessine le profil ; mouvante, elle s’oppose au statisme et à la pérennité du visage. L’influence de Van Gogh est nette : la touche, les empâtements de rouge, jaune, vert et bleu. » (Marie-Laure Bernadac, Musée Picasso Paris, Les chefs d’œuvre, p. 18)."
              },
              {
              "id": "6",
              "title": "Autoportrait",
              "sceneNumber": "2",
              "year": "1900",
              "h": "20 m",
              "l": "30 m",
              "technical": "Huiles sur toile",
              "description": "Cet autoportrait est la poursuite du cycle sur Casagemas comme le souligne Pierre Daix : « Cet autoportrait, toujours conservé par Picasso le montre tel qu’il s’est vu après le retour sur soi du Cycle de la mort de Casagemas en apprenant que Manyac, qui l’avait jusque-là soutenu financièrement lui coupait les vivres. Celui-ci désapprouvait le tournant que prenait la peinture de Picasso vers ce que l’on appelle à présent la « période bleue » et dont les thèmes, le malheur et la détresse, éloignaient les acheteurs. C’est en quelque sorte un autoportrait au futur dans la misère qui ne manquerait pas de le guetter, au milieu de l’hiver si inclément de Paris. Mais s’il n’a évidemment jamais porté cette moustache et cette barbe blonde qu’il peint avec des finesses de miniaturiste pour aggraver l’aspect hâve, creusé par la faim, de son visage, nous savons aujourd’hui à quel point il s’est alors « donné » cette tête-là. »  (Pierre Daix, Le nouveau dictionnaire Picasso, p. 68). Marie-Laure Bernadac revient sur l’importance de l’autoportrait dans l’œuvre picassien : « S’inscrivant dans la lignée de l’œuvre de ses illustres prédécesseurs (Rembrandt, Van Gogh) Picasso marque pour ce thème une prédilection, puisque l’on retrouvera tout au long de sa longue existence, des images distinctes de lui-même, révélatrices de chaque étape de sa vie et de son œuvre. Peint lors du second séjour à Paris, en hiver 1901, cet autoportrait qui marque le début de la période bleue est le dernier d’une série, avant le départ pour Barcelone en janvier 1902. » (Marie-Laure Bernadac, Musée Picasso Paris, Les chefs d’œuvre, p. 20)."
              },
              {
              "id": "7",
              "title": "Autoportrait, automne 1906",
              "sceneNumber": "2",
              "year": "1900",
              "h": "20 m",
              "l": "30 m",
              "technical": "Huiles sur toile",
              "description": "Pour Pierre Daix, Picasso a toujours pris « son visage comme banc d’essai de ses percées figuratives. L’entreprise de réduction du visage à son masque a commencé au début de l’été 1906 à Gosol sur le visage de (…) Fernande, à partir d’une réflexion sur les sculptures ibériques révélées au Louvre fin 1905. Elle aboutit à Paros à toute une série d’autoportraits où Picasso réduit son propre visage à son masque, c’est-à-dire à des volumes neutralisés. (…) En dépit de cette première référence à l’art nègre – mais à l’époque pour Picasso, le primitivisme est une recherche générale où se confondent des éléments venus de sources pour nous géographiquement et historiquement différentes –, les autoportraits de cette séquence sont essentiellement ibériques. La chevelure est toujours réduite au minimum, à son insertion sur la tête. Le cou est massif et le buste statique. » (Pierre Daix, Le nouveau dictionnaire Picasso, p. 72). Marie-Laure Bernadac précise que ce corps est « comme une architecture : c’est un carré délimité par trois traits sombres formés par les arêtes des bras et les clavicules ; dont le centre coïncide avec le croisement des muscles pectoraux et de la ligne médiane du buste. Le cou est traité comme un cylindre (…). » (Marie-Laure Bernadac, Musée Picasso Paris, Les chefs d’œuvre, p. 28)."
              },
              {
              "id": "8",
              "title": "La fillette aux pieds nus",
              "sceneNumber": "2",
              "year": "1900",
              "h": "20 m",
              "l": "30 m",
              "technical": "Huiles sur toile",
              "description": "Cette œuvre est un témoignage de sa précocité, comme le souligne Pierre Daix : « témoignage de sa précocité, et peut être aussi souvenir d’une émotion d’adolescent puisqu’il n’avait pas quatorze ans lorsqu’il la peignit « La fillette aux pieds nus atteste un métier affirmé jusqu’aux roueries pour camper cette figure assise de face en dissimulant les repères spatiaux de la chaise sur le sol. Ce qui a intéressé Pablo, ce n’est pas pourtant la seule technique, c’est d’interroger al vie de ce modèle de son âge, de vouloir à tout prix capter son avenir de femme et de la capter d’avance par ses pinceaux. Précocité déjà effrayante… » (Daix, 1987,19). Ajoutons que la Fillette anticipe sur ces centaines de « femmes assises » qu’on retrouvera tout au long de l’œuvre comme une obsession de la peinture ». (Pierre Daix, Le nouveau dictionnaire Picasso, p. 369). Joseph Palau i Fabre souligne que dans ce tableau de jeunesse « se révèlent à la fois la sympathie pour ses modèles et l’attrait de la femme, même si la féminité de cette petite mendiante est encore embryonnaire et triste. Picasso réalisa ce tableau d’après un modèle vivant dont les parents louèrent les services, montrant là l’intérêt qu’ils attachaient à la vocation de leur fils dont ils souhaitaient l’aider à prendre lui-même pleine conscience. A propos de ce tableau, le peintre déclara à Antonina Vallentin « Les pauvresses de notre pays vont toujours pieds nus, et cette fillette avait les siens couverts de cals ». (Val, P, p.20).  Cette fillette aux pieds nus, en pied au regard asymétrique bien observé, à la bouche légèrement désabusée, semble comme le nostalgique adieu de Picasso à une période de sa vie. Son premier face-à-face avec la femme est traduit avec une intense expressivité : la fillette regarde et voit autant qu’elle est regardée et vue. Ici s’ébauche déjà le problème du peintre et son modèle, que bien plus tard Picasso devait affronter à plusieurs reprises. Il ya  là deux adolescents à peu près du même âge, l’un devant l’autre, qui ne purent se dire par leur regard ce qu’ils auraient pu se dire de vive voix. Mais ces yeux ont gardé, malgré le passage du temps, toute la force d’attraction qu’ils possédaient ou que Picasso sut mettre en eux ». (Joseph Palau i Fabre, Picasso vivant. Enfance et première jeunesse d’un démiurge. 1881-1907, p.63)."
              },
              {
              "id": "9",
              "title": "La mort de Casagemas",
              "sceneNumber": "3",
              "year": "1900",
              "h": "20 m",
              "l": "30 m",
              "technical": "Huiles sur toile",
              "description": "« Le suicide de son ami Casagemas le 17 février 1901, poussa Picasso à créer tout un ensemble de tableaux dont il conserva secrètement les trois premiers jusqu’en 1965 quand il le fit reproduire dans D-B. Le premier est La mort de Casagemas, dans la palette haute en couleurs de l’exposition chez Vollard, qui doit dater de l’été 1901. Casagemas dans son cercueil et Portrait de Casagemas mort marquent l’emprise progressive du bleu (…). Ce cycle illustre la précision de la remarque de Picasso : « C’est en pensant que Casagemas était mort que je me suis mis à peindre en bleu ». (Daix, 1975, 47à) ». (Pierre Daix, Le nouveau dictionnaire Picasso, p. 228). Marie-Laure Bernadac a qualifié la mort de cet ami de sujet obsessionnel : « Cette mort va obséder progressivement Picasso. Pour l’exorciser, il réalise une série de portraits posthumes, sept toiles et de multiples dessins. (…). Le suicidé (le thème de la mort violente est fréquent dans l’art espagnol) est enveloppé dans un linceul, seul le visage vu de profil sort de l’écume. Casagemas est peint en grand plan, sur sa tempe une tache sombre, l’impact de la balle. Cassant le mouvement oblique une énorme chandelle verticale illumine tout le tableau. Symbole de l’écoulement de la vie, la bougie reviendra dans les nature-mortes de la seconde guerre mondiale. La lumière se répand sur le linceul par taches jaunes et dessine le profil ; mouvante, elle s’oppose au statisme et à la pérennité du visage. L’influence de Van Gogh est nette : la touche, les empâtements de rouge, jaune, vert et bleu. » (Marie-Laure Bernadac, Musée Picasso Paris, Les chefs d’œuvre, p. 18)."
              },
              {
              "id": "10",
              "title": "Autoportrait",
              "sceneNumber": "3",
              "year": "1900",
              "h": "20 m",
              "l": "30 m",
              "technical": "Huiles sur toile",
              "description": "Cet autoportrait est la poursuite du cycle sur Casagemas comme le souligne Pierre Daix : « Cet autoportrait, toujours conservé par Picasso le montre tel qu’il s’est vu après le retour sur soi du Cycle de la mort de Casagemas en apprenant que Manyac, qui l’avait jusque-là soutenu financièrement lui coupait les vivres. Celui-ci désapprouvait le tournant que prenait la peinture de Picasso vers ce que l’on appelle à présent la « période bleue » et dont les thèmes, le malheur et la détresse, éloignaient les acheteurs. C’est en quelque sorte un autoportrait au futur dans la misère qui ne manquerait pas de le guetter, au milieu de l’hiver si inclément de Paris. Mais s’il n’a évidemment jamais porté cette moustache et cette barbe blonde qu’il peint avec des finesses de miniaturiste pour aggraver l’aspect hâve, creusé par la faim, de son visage, nous savons aujourd’hui à quel point il s’est alors « donné » cette tête-là. »  (Pierre Daix, Le nouveau dictionnaire Picasso, p. 68). Marie-Laure Bernadac revient sur l’importance de l’autoportrait dans l’œuvre picassien : « S’inscrivant dans la lignée de l’œuvre de ses illustres prédécesseurs (Rembrandt, Van Gogh) Picasso marque pour ce thème une prédilection, puisque l’on retrouvera tout au long de sa longue existence, des images distinctes de lui-même, révélatrices de chaque étape de sa vie et de son œuvre. Peint lors du second séjour à Paris, en hiver 1901, cet autoportrait qui marque le début de la période bleue est le dernier d’une série, avant le départ pour Barcelone en janvier 1902. » (Marie-Laure Bernadac, Musée Picasso Paris, Les chefs d’œuvre, p. 20)."
              }
              ]
}